yarr_client
