Metadata-Version: 1.1
Name: yarr.client
Version: 0.2.1
Summary: Web-based client for Yarr!
Home-page: https://github.com/bluecap-se/yarr.client
Author: bluecap-se
Author-email: hello@bluecap.se
License: MIT
Keywords: yarr,the pirate bay,web based,client
Platform: any
Classifier: Development Status :: 5 - Production/Stable
Classifier: Environment :: Web Environment
Classifier: Framework :: Flask
Classifier: Intended Audience :: End Users/Desktop
Classifier: License :: OSI Approved :: MIT License
Classifier: Natural Language :: English
Classifier: Operating System :: MacOS
Classifier: Operating System :: POSIX
Classifier: Programming Language :: Python :: 2 :: Only
Classifier: Topic :: Internet :: WWW/HTTP :: Indexing/Search
